MANIFEST.in
setup.py
django_ini_settings/METADATA
django_ini_settings/__init__.py
django_ini_settings/load.py
django_ini_settings/settings_types.py
django_ini_settings/statics.py
django_ini_settings.egg-info/PKG-INFO
django_ini_settings.egg-info/SOURCES.txt
django_ini_settings.egg-info/dependency_links.txt
django_ini_settings.egg-info/top_level.txt
test/test_load.py
test/test_settings_types.py