Metadata-Version: 1.0
Name: django-ini-settings
Version: 0.0.1
Summary: A configurable way of moving some settings out of the django settings.py and into a deployable .ini file
Home-page: UNKNOWN
Author: Sebastian Phelps
Author-email: sebastian.phelps@gmail.com
License: UNKNOWN
Keywords: django_ini_settings django local settings ini
Platform: UNKNOWN
